pyballc/__init__.py
pyballc/parser.py
pyballc/pyballc.py
pyballc/settings.py
pyballc-0.9.0.dist-info/METADATA
pyballc-0.9.0.dist-info/WHEEL
pyballc-0.9.0.dist-info/top_level.txt
pyballc-0.9.0.dist-info/RECORD
