Metadata-Version: 2.1
Name: pyballc
Version: 0.9.0
Summary: Python module for reading BAllC files
Home-page: https://github.com/jksr/pyballc
Author: Wei Tian
Author-email: jksr.tw@gmail.com
Classifier: Programming Language :: Python :: 3
Classifier: Operating System :: OS Independent
Requires-Python: >=3.7
